odoo/addons/ssi_fleet_work_order_stock/README.rst
odoo/addons/ssi_fleet_work_order_stock/__init__.py
odoo/addons/ssi_fleet_work_order_stock/__manifest__.py
odoo/addons/ssi_fleet_work_order_stock/models/__init__.py
odoo/addons/ssi_fleet_work_order_stock/models/fleet_work_order.py
odoo/addons/ssi_fleet_work_order_stock/models/fleet_work_order_manifest.py
odoo/addons/ssi_fleet_work_order_stock/models/fleet_work_order_type.py
odoo/addons/ssi_fleet_work_order_stock/models/stock_picking.py
odoo/addons/ssi_fleet_work_order_stock/security/ir.model.access.csv
odoo/addons/ssi_fleet_work_order_stock/static/description/icon.png
odoo/addons/ssi_fleet_work_order_stock/views/fleet_work_order_type_views.xml
odoo/addons/ssi_fleet_work_order_stock/views/fleet_work_order_views.xml
odoo14_addon_ssi_fleet_work_order_stock-14.0.2.5.0.dist-info/METADATA
odoo14_addon_ssi_fleet_work_order_stock-14.0.2.5.0.dist-info/WHEEL
odoo14_addon_ssi_fleet_work_order_stock-14.0.2.5.0.dist-info/top_level.txt
odoo14_addon_ssi_fleet_work_order_stock-14.0.2.5.0.dist-info/RECORD
